{"_id":"4mtQQ0kWM59tEMhvK_aETCCGNLtsskdD","expires":{"$date":"2020-07-16T21:45:31.502Z"},"session":"{\"cookie\":{\"originalMaxAge\":null,\"expires\":null,\"httpOnly\":true,\"path\":\"/\"},\"_csrf_secret\":\"zpAgTSM62/WsQQ==\"}"}
{"_id":"GrvRIpVdaATr0oGt7ZKT8VYJUztoTux7","expires":{"$date":"2020-07-14T19:23:20.995Z"},"session":"{\"cookie\":{\"originalMaxAge\":null,\"expires\":null,\"httpOnly\":true,\"path\":\"/\"},\"_csrf_secret\":\"w+tttqd4UViz4w==\"}"}
{"_id":"HOYVvZUFrbCap0lENhYxYj7Ir197ONOR","expires":{"$date":"2020-07-15T15:58:43.798Z"},"session":"{\"cookie\":{\"originalMaxAge\":null,\"expires\":null,\"httpOnly\":true,\"path\":\"/\"},\"_csrf_secret\":\"ipmGMjTLjbbPfQ==\"}"}
{"_id":"LCdSJqfMJvrN1mBxNm_EWLto-GGkbOUU","expires":{"$date":"2020-07-13T20:46:52.109Z"},"session":"{\"cookie\":{\"originalMaxAge\":null,\"expires\":null,\"httpOnly\":true,\"path\":\"/\"},\"_csrf_secret\":\"N40fVBTjLvr8sA==\"}"}
{"_id":"aVnDbcjd5s8jH1Ntr1gnIVohDU7bydmS","expires":{"$date":"2020-07-16T21:46:56.535Z"},"session":"{\"cookie\":{\"originalMaxAge\":null,\"expires\":null,\"httpOnly\":true,\"path\":\"/\"},\"_csrf_secret\":\"W+ugdLk/ceo4SA==\"}"}
{"_id":"b7juvK2QvsVkLTksdhWTFCtUkfOGVDVc","expires":{"$date":"2020-07-13T21:47:02.112Z"},"session":"{\"cookie\":{\"originalMaxAge\":null,\"expires\":null,\"httpOnly\":true,\"path\":\"/\"},\"_csrf_secret\":\"ovy5Hyv1zgYpow==\"}"}
{"_id":"naJAf_1HngBD-v-IqdFSX0AKgSc0JNof","expires":{"$date":"2020-07-14T19:21:00.942Z"},"session":"{\"cookie\":{\"originalMaxAge\":null,\"expires\":null,\"httpOnly\":true,\"path\":\"/\"},\"_csrf_secret\":\"E9E05aQrx+jvLw==\"}"}
{"_id":"tWS1NdLQ4SioPIrTjuHErD9TR4YUUpig","expires":{"$date":"2020-07-13T21:46:15.485Z"},"session":"{\"cookie\":{\"originalMaxAge\":null,\"expires\":null,\"httpOnly\":true,\"path\":\"/\"},\"_csrf_secret\":\"/NNHZOIlPqSkjQ==\"}"}
{"_id":"ttMQmLQGpQUFl07oAWR8-i1SNbj2MQLW","expires":{"$date":"2020-07-14T18:10:56.905Z"},"session":"{\"cookie\":{\"originalMaxAge\":null,\"expires\":null,\"httpOnly\":true,\"path\":\"/\"},\"_csrf_secret\":\"gsBzPdVJAtTWiw==\"}"}
{"_id":"ywWen6FxVamE9Dwq2ShCGIZ0zKYCp40W","expires":{"$date":"2020-07-14T18:45:02.380Z"},"session":"{\"cookie\":{\"originalMaxAge\":null,\"expires\":null,\"httpOnly\":true,\"path\":\"/\"},\"_csrf_secret\":\"AV5IVzOE8mSTFw==\"}"}
